{
  "meta": {
    "title": "11+ Maths Flashcards - Times Tables",
    "version": "1.0"
  },
  "deck": {
    "id": "times-tables",
    "name": "Times Tables 0-12",
    "cards": [
      { "id": "tt-0x0", "question": "What is 0 x 0?", "answer": "0", "tags": ["times-table","0"] },
      { "id": "tt-0x1", "question": "What is 0 x 1?", "answer": "0", "tags": ["times-table","0"] },
      { "id": "tt-0x2", "question": "What is 0 x 2?", "answer": "0", "tags": ["times-table","0"] },
      { "id": "tt-0x3", "question": "What is 0 x 3?", "answer": "0", "tags": ["times-table","0"] },
      { "id": "tt-0x4", "question": "What is 0 x 4?", "answer": "0", "tags": ["times-table","0"] },
      { "id": "tt-0x5", "question": "What is 0 x 5?", "answer": "0", "tags": ["times-table","0"] },
      { "id": "tt-0x6", "question": "What is 0 x 6?", "answer": "0", "tags": ["times-table","0"] },
      { "id": "tt-0x7", "question": "What is 0 x 7?", "answer": "0", "tags": ["times-table","0"] },
      { "id": "tt-0x8", "question": "What is 0 x 8?", "answer": "0", "tags": ["times-table","0"] },
      { "id": "tt-0x9", "question": "What is 0 x 9?", "answer": "0", "tags": ["times-table","0"] },
      { "id": "tt-0x10", "question": "What is 0 x 10?", "answer": "0", "tags": ["times-table","0"] },
      { "id": "tt-0x11", "question": "What is 0 x 11?", "answer": "0", "tags": ["times-table","0"] },
      { "id": "tt-0x12", "question": "What is 0 x 12?", "answer": "0", "tags": ["times-table","0"] },
      { "id": "tt-1x0", "question": "What is 1 x 0?", "answer": "0", "tags": ["times-table","1"] },
      { "id": "tt-1x1", "question": "What is 1 x 1?", "answer": "1", "tags": ["times-table","1"] },
      { "id": "tt-1x2", "question": "What is 1 x 2?", "answer": "2", "tags": ["times-table","1"] },
      { "id": "tt-1x3", "question": "What is 1 x 3?", "answer": "3", "tags": ["times-table","1"] },
      { "id": "tt-1x4", "question": "What is 1 x 4?", "answer": "4", "tags": ["times-table","1"] },
      { "id": "tt-1x5", "question": "What is 1 x 5?", "answer": "5", "tags": ["times-table","1"] },
      { "id": "tt-1x6", "question": "What is 1 x 6?", "answer": "6", "tags": ["times-table","1"] },
      { "id": "tt-1x7", "question": "What is 1 x 7?", "answer": "7", "tags": ["times-table","1"] },
      { "id": "tt-1x8", "question": "What is 1 x 8?", "answer": "8", "tags": ["times-table","1"] },
      { "id": "tt-1x9", "question": "What is 1 x 9?", "answer": "9", "tags": ["times-table","1"] },
      { "id": "tt-1x10", "question": "What is 1 x 10?", "answer": "10", "tags": ["times-table","1"] },
      { "id": "tt-1x11", "question": "What is 1 x 11?", "answer": "11", "tags": ["times-table","1"] },
      { "id": "tt-1x12", "question": "What is 1 x 12?", "answer": "12", "tags": ["times-table","1"] },
      { "id": "tt-2x0", "question": "What is 2 x 0?", "answer": "0", "tags": ["times-table","2"] },
      { "id": "tt-2x1", "question": "What is 2 x 1?", "answer": "2", "tags": ["times-table","2"] },
      { "id": "tt-2x2", "question": "What is 2 x 2?", "answer": "4", "tags": ["times-table","2"] },
      { "id": "tt-2x3", "question": "What is 2 x 3?", "answer": "6", "tags": ["times-table","2"] },
      { "id": "tt-2x4", "question": "What is 2 x 4?", "answer": "8", "tags": ["times-table","2"] },
      { "id": "tt-2x5", "question": "What is 2 x 5?", "answer": "10", "tags": ["times-table","2"] },
      { "id": "tt-2x6", "question": "What is 2 x 6?", "answer": "12", "tags": ["times-table","2"] },
      { "id": "tt-2x7", "question": "What is 2 x 7?", "answer": "14", "tags": ["times-table","2"] },
      { "id": "tt-2x8", "question": "What is 2 x 8?", "answer": "16", "tags": ["times-table","2"] },
      { "id": "tt-2x9", "question": "What is 2 x 9?", "answer": "18", "tags": ["times-table","2"] },
      { "id": "tt-2x10", "question": "What is 2 x 10?", "answer": "20", "tags": ["times-table","2"] },
      { "id": "tt-2x11", "question": "What is 2 x 11?", "answer": "22", "tags": ["times-table","2"] },
      { "id": "tt-2x12", "question": "What is 2 x 12?", "answer": "24", "tags": ["times-table","2"] },
      { "id": "tt-2x12", "question": "What is 2 x 12?", "answer": "24", "tags": ["times-table","2"] },
      { "id": "tt-3x0", "question": "What is 3 x 0?", "answer": "0", "tags": ["times-table","3"] },
      { "id": "tt-3x1", "question": "What is 3 x 1?", "answer": "3", "tags": ["times-table","3"] },
      { "id": "tt-3x2", "question": "What is 3 x 2?", "answer": "6", "tags": ["times-table","3"] },
      { "id": "tt-3x3", "question": "What is 3 x 3?", "answer": "9", "tags": ["times-table","3"] },
      { "id": "tt-3x4", "question": "What is 3 x 4?", "answer": "12", "tags": ["times-table","3"] },
      { "id": "tt-3x5", "question": "What is 3 x 5?", "answer": "15", "tags": ["times-table","3"] },
      { "id": "tt-3x6", "question": "What is 3 x 6?", "answer": "18", "tags": ["times-table","3"] },
      { "id": "tt-3x7", "question": "What is 3 x 7?", "answer": "21", "tags": ["times-table","3"] },
      { "id": "tt-3x8", "question": "What is 3 x 8?", "answer": "24", "tags": ["times-table","3"] },
      { "id": "tt-3x9", "question": "What is 3 x 9?", "answer": "27", "tags": ["times-table","3"] },
      { "id": "tt-3x10", "question": "What is 3 x 10?", "answer": "30", "tags": ["times-table","3"] },
      { "id": "tt-3x11", "question": "What is 3 x 11?", "answer": "33", "tags": ["times-table","3"] },
      { "id": "tt-3x12", "question": "What is 3 x 12?", "answer": "36", "tags": ["times-table","3"] },
      { "id": "tt-4x0", "question": "What is 4 x 0?", "answer": "0", "tags": ["times-table","4"] },
      { "id": "tt-4x1", "question": "What is 4 x 1?", "answer": "4", "tags": ["times-table","4"] },
      { "id": "tt-4x2", "question": "What is 4 x 2?", "answer": "8", "tags": ["times-table","4"] },
      { "id": "tt-4x3", "question": "What is 4 x 3?", "answer": "12", "tags": ["times-table","4"] },
      { "id": "tt-4x4", "question": "What is 4 x 4?", "answer": "16", "tags": ["times-table","4"] },
      { "id": "tt-4x5", "question": "What is 4 x 5?", "answer": "20", "tags": ["times-table","4"] },
      { "id": "tt-4x6", "question": "What is 4 x 6?", "answer": "24", "tags": ["times-table","4"] },
      { "id": "tt-4x7", "question": "What is 4 x 7?", "answer": "28", "tags": ["times-table","4"] },
      { "id": "tt-4x8", "question": "What is 4 x 8?", "answer": "32", "tags": ["times-table","4"] },
      { "id": "tt-4x9", "question": "What is 4 x 9?", "answer": "36", "tags": ["times-table","4"] },
      { "id": "tt-4x10", "question": "What is 4 x 10?", "answer": "40", "tags": ["times-table","4"] },
      { "id": "tt-4x11", "question": "What is 4 x 11?", "answer": "44", "tags": ["times-table","4"] },
      { "id": "tt-4x12", "question": "What is 4 x 12?", "answer": "48", "tags": ["times-table","4"] },
      { "id": "tt-4x12", "question": "What is 4 x 12?", "answer": "48", "tags": ["times-table","4"] },
      { "id": "tt-5x0", "question": "What is 5 x 0?", "answer": "0", "tags": ["times-table","5"] },
      { "id": "tt-5x1", "question": "What is 5 x 1?", "answer": "5", "tags": ["times-table","5"] },
      { "id": "tt-5x2", "question": "What is 5 x 2?", "answer": "10", "tags": ["times-table","5"] },
      { "id": "tt-5x3", "question": "What is 5 x 3?", "answer": "15", "tags": ["times-table","5"] },
      { "id": "tt-5x4", "question": "What is 5 x 4?", "answer": "20", "tags": ["times-table","5"] },
      { "id": "tt-5x5", "question": "What is 5 x 5?", "answer": "25", "tags": ["times-table","5"] },
      { "id": "tt-5x6", "question": "What is 5 x 6?", "answer": "30", "tags": ["times-table","5"] },
      { "id": "tt-5x7", "question": "What is 5 x 7?", "answer": "35", "tags": ["times-table","5"] },
      { "id": "tt-5x8", "question": "What is 5 x 8?", "answer": "40", "tags": ["times-table","5"] },
      { "id": "tt-5x9", "question": "What is 5 x 9?", "answer": "45", "tags": ["times-table","5"] },
      { "id": "tt-5x10", "question": "What is 5 x 10?", "answer": "50", "tags": ["times-table","5"] },
      { "id": "tt-5x11", "question": "What is 5 x 11?", "answer": "55", "tags": ["times-table","5"] },
      { "id": "tt-5x12", "question": "What is 5 x 12?", "answer": "60", "tags": ["times-table","5"] },
      { "id": "tt-6x0", "question": "What is 6 x 0?", "answer": "0", "tags": ["times-table","6"] },
      { "id": "tt-6x1", "question": "What is 6 x 1?", "answer": "6", "tags": ["times-table","6"] },
      { "id": "tt-6x2", "question": "What is 6 x 2?", "answer": "12", "tags": ["times-table","6"] },
      { "id": "tt-6x3", "question": "What is 6 x 3?", "answer": "18", "tags": ["times-table","6"] },
      { "id": "tt-6x4", "question": "What is 6 x 4?", "answer": "24", "tags": ["times-table","6"] },
      { "id": "tt-6x5", "question": "What is 6 x 5?", "answer": "30", "tags": ["times-table","6"] },
      { "id": "tt-6x6", "question": "What is 6 x 6?", "answer": "36", "tags": ["times-table","6"] },
      { "id": "tt-6x7", "question": "What is 6 x 7?", "answer": "42", "tags": ["times-table","6"] },
      { "id": "tt-6x8", "question": "What is 6 x 8?", "answer": "48", "tags": ["times-table","6"] },
      { "id": "tt-6x9", "question": "What is 6 x 9?", "answer": "54", "tags": ["times-table","6"] },
      { "id": "tt-6x10", "question": "What is 6 x 10?", "answer": "60", "tags": ["times-table","6"] },
      { "id": "tt-6x11", "question": "What is 6 x 11?", "answer": "66", "tags": ["times-table","6"] },
      { "id": "tt-6x12", "question": "What is 6 x 12?", "answer": "72", "tags": ["times-table","6"] },
      { "id": "tt-6x12", "question": "What is 6 x 12?", "answer": "72", "tags": ["times-table","6"] },
      { "id": "tt-7x0", "question": "What is 7 x 0?", "answer": "0", "tags": ["times-table","7"] },
      { "id": "tt-7x1", "question": "What is 7 x 1?", "answer": "7", "tags": ["times-table","7"] },
      { "id": "tt-7x2", "question": "What is 7 x 2?", "answer": "14", "tags": ["times-table","7"] },
      { "id": "tt-7x3", "question": "What is 7 x 3?", "answer": "21", "tags": ["times-table","7"] },
      { "id": "tt-7x4", "question": "What is 7 x 4?", "answer": "28", "tags": ["times-table","7"] },
      { "id": "tt-7x5", "question": "What is 7 x 5?", "answer": "35", "tags": ["times-table","7"] },
      { "id": "tt-7x6", "question": "What is 7 x 6?", "answer": "42", "tags": ["times-table","7"] },
      { "id": "tt-7x7", "question": "What is 7 x 7?", "answer": "49", "tags": ["times-table","7"] },
      { "id": "tt-7x8", "question": "What is 7 x 8?", "answer": "56", "tags": ["times-table","7"] },
      { "id": "tt-7x9", "question": "What is 7 x 9?", "answer": "63", "tags": ["times-table","7"] },
      { "id": "tt-7x10", "question": "What is 7 x 10?", "answer": "70", "tags": ["times-table","7"] },
      { "id": "tt-7x11", "question": "What is 7 x 11?", "answer": "77", "tags": ["times-table","7"] },
      { "id": "tt-7x12", "question": "What is 7 x 12?", "answer": "84", "tags": ["times-table","7"] },
      { "id": "tt-8x0", "question": "What is 8 x 0?", "answer": "0", "tags": ["times-table","8"] },
      { "id": "tt-8x1", "question": "What is 8 x 1?", "answer": "8", "tags": ["times-table","8"] },
      { "id": "tt-8x2", "question": "What is 8 x 2?", "answer": "16", "tags": ["times-table","8"] },
      { "id": "tt-8x3", "question": "What is 8 x 3?", "answer": "24", "tags": ["times-table","8"] },
      { "id": "tt-8x4", "question": "What is 8 x 4?", "answer": "32", "tags": ["times-table","8"] },
      { "id": "tt-8x5", "question": "What is 8 x 5?", "answer": "40", "tags": ["times-table","8"] },
      { "id": "tt-8x6", "question": "What is 8 x 6?", "answer": "48", "tags": ["times-table","8"] },
      { "id": "tt-8x7", "question": "What is 8 x 7?", "answer": "56", "tags": ["times-table","8"] },
      { "id": "tt-8x8", "question": "What is 8 x 8?", "answer": "64", "tags": ["times-table","8"] },
      { "id": "tt-8x9", "question": "What is 8 x 9?", "answer": "72", "tags": ["times-table","8"] },
      { "id": "tt-8x10", "question": "What is 8 x 10?", "answer": "80", "tags": ["times-table","8"] },
      { "id": "tt-8x11", "question": "What is 8 x 11?", "answer": "88", "tags": ["times-table","8"] },
      { "id": "tt-8x12", "question": "What is 8 x 12?", "answer": "96", "tags": ["times-table","8"] },
      { "id": "tt-8x12", "question": "What is 8 x 12?", "answer": "96", "tags": ["times-table","8"] },
      { "id": "tt-9x0", "question": "What is 9 x 0?", "answer": "0", "tags": ["times-table","9"] },
      { "id": "tt-9x1", "question": "What is 9 x 1?", "answer": "9", "tags": ["times-table","9"] },
      { "id": "tt-9x2", "question": "What is 9 x 2?", "answer": "18", "tags": ["times-table","9"] },
      { "id": "tt-9x3", "question": "What is 9 x 3?", "answer": "27", "tags": ["times-table","9"] },
      { "id": "tt-9x4", "question": "What is 9 x 4?", "answer": "36", "tags": ["times-table","9"] },
      { "id": "tt-9x5", "question": "What is 9 x 5?", "answer": "45", "tags": ["times-table","9"] },
      { "id": "tt-9x6", "question": "What is 9 x 6?", "answer": "54", "tags": ["times-table","9"] },
      { "id": "tt-9x7", "question": "What is 9 x 7?", "answer": "63", "tags": ["times-table","9"] },
      { "id": "tt-9x8", "question": "What is 9 x 8?", "answer": "72", "tags": ["times-table","9"] },
      { "id": "tt-9x9", "question": "What is 9 x 9?", "answer": "81", "tags": ["times-table","9"] },
      { "id": "tt-9x10", "question": "What is 9 x 10?", "answer": "90", "tags": ["times-table","9"] },
      { "id": "tt-9x11", "question": "What is 9 x 11?", "answer": "99", "tags": ["times-table","9"] },
      { "id": "tt-9x12", "question": "What is 9 x 12?", "answer": "108", "tags": ["times-table","9"] },
      { "id": "tt-10x0", "question": "What is 10 x 0?", "answer": "0", "tags": ["times-table","10"] },
      { "id": "tt-10x1", "question": "What is 10 x 1?", "answer": "10", "tags": ["times-table","10"] },
      { "id": "tt-10x2", "question": "What is 10 x 2?", "answer": "20", "tags": ["times-table","10"] },
      { "id": "tt-10x3", "question": "What is 10 x 3?", "answer": "30", "tags": ["times-table","10"] },
      { "id": "tt-10x4", "question": "What is 10 x 4?", "answer": "40", "tags": ["times-table","10"] },
      { "id": "tt-10x5", "question": "What is 10 x 5?", "answer": "50", "tags": ["times-table","10"] },
      { "id": "tt-10x6", "question": "What is 10 x 6?", "answer": "60", "tags": ["times-table","10"] },
      { "id": "tt-10x7", "question": "What is 10 x 7?", "answer": "70", "tags": ["times-table","10"] },
      { "id": "tt-10x8", "question": "What is 10 x 8?", "answer": "80", "tags": ["times-table","10"] },
      { "id": "tt-10x9", "question": "What is 10 x 9?", "answer": "90", "tags": ["times-table","10"] },
      { "id": "tt-10x10", "question": "What is 10 x 10?", "answer": "100", "tags": ["times-table","10"] },
      { "id": "tt-10x11", "question": "What is 10 x 11?", "answer": "110", "tags": ["times-table","10"] },
      { "id": "tt-10x12", "question": "What is 10 x 12?", "answer": "120", "tags": ["times-table","10"] },
      { "id": "tt-10x12", "question": "What is 10 x 12?", "answer": "120", "tags": ["times-table","10"] },
      { "id": "tt-11x0", "question": "What is 11 x 0?", "answer": "0", "tags": ["times-table","11"] },
      { "id": "tt-11x1", "question": "What is 11 x 1?", "answer": "11", "tags": ["times-table","11"] },
      { "id": "tt-11x2", "question": "What is 11 x 2?", "answer": "22", "tags": ["times-table","11"] },
      { "id": "tt-11x3", "question": "What is 11 x 3?", "answer": "33", "tags": ["times-table","11"] },
      { "id": "tt-11x4", "question": "What is 11 x 4?", "answer": "44", "tags": ["times-table","11"] },
      { "id": "tt-11x5", "question": "What is 11 x 5?", "answer": "55", "tags": ["times-table","11"] },
      { "id": "tt-11x6", "question": "What is 11 x 6?", "answer": "66", "tags": ["times-table","11"] },
      { "id": "tt-11x7", "question": "What is 11 x 7?", "answer": "77", "tags": ["times-table","11"] },
      { "id": "tt-11x8", "question": "What is 11 x 8?", "answer": "88", "tags": ["times-table","11"] },
      { "id": "tt-11x9", "question": "What is 11 x 9?", "answer": "99", "tags": ["times-table","11"] },
      { "id": "tt-11x10", "question": "What is 11 x 10?", "answer": "110", "tags": ["times-table","11"] },
      { "id": "tt-11x11", "question": "What is 11 x 11?", "answer": "121", "tags": ["times-table","11"] },
      { "id": "tt-11x12", "question": "What is 11 x 12?", "answer": "132", "tags": ["times-table","11"] },
      { "id": "tt-12x0", "question": "What is 12 x 0?", "answer": "0", "tags": ["times-table","12"] },
      { "id": "tt-12x1", "question": "What is 12 x 1?", "answer": "12", "tags": ["times-table","12"] },
      { "id": "tt-12x2", "question": "What is 12 x 2?", "answer": "24", "tags": ["times-table","12"] },
      { "id": "tt-12x3", "question": "What is 12 x 3?", "answer": "36", "tags": ["times-table","12"] },
      { "id": "tt-12x4", "question": "What is 12 x 4?", "answer": "48", "tags": ["times-table","12"] },
      { "id": "tt-12x5", "question": "What is 12 x 5?", "answer": "60", "tags": ["times-table","12"] },
      { "id": "tt-12x6", "question": "What is 12 x 6?", "answer": "72", "tags": ["times-table","12"] },
      { "id": "tt-12x7", "question": "What is 12 x 7?", "answer": "84", "tags": ["times-table","12"] },
      { "id": "tt-12x8", "question": "What is 12 x 8?", "answer": "96", "tags": ["times-table","12"] },
      { "id": "tt-12x9", "question": "What is 12 x 9?", "answer": "108", "tags": ["times-table","12"] },
      { "id": "tt-12x10", "question": "What is 12 x 10?", "answer": "120", "tags": ["times-table","12"] },
      { "id": "tt-12x11", "question": "What is 12 x 11?", "answer": "132", "tags": ["times-table","12"] },
      { "id": "tt-12x12", "question": "What is 12 x 12?", "answer": "144", "tags": ["times-table","12"] }
    ]
  }
}
